ngiridb/__init__.py
ngiridb/core.py
ngiridb/importer.py
ngiridb/interfaces.py
ngiridb/py.typed
ngiridb/backends/__init__.py
ngiridb/backends/aiopg.py
ngiridb/backends/asyncmy.py
ngiridb/backends/mysql.py
ngiridb/backends/postgres.py
ngiridb/backends/sqlite.py
ngiridb-0.0.1.dist-info/LICENSE
ngiridb-0.0.1.dist-info/METADATA
ngiridb-0.0.1.dist-info/WHEEL
ngiridb-0.0.1.dist-info/top_level.txt
ngiridb-0.0.1.dist-info/RECORD
