Metadata-Version: 2.1
Name: ngiridb
Version: 0.0.1
Summary: Mult Async database for Python.
Home-page: https://github.com/pesaply/ngiridb
Author: Mark Francis
Author-email: ngiriapp@gmail.com
License: BSD
Classifier: Development Status :: 3 - Alpha
Classifier: Environment :: Web Environment
Classifier: Intended Audience :: Developers
Classifier: License :: OSI Approved :: BSD License
Classifier: Operating System :: OS Independent
Classifier: Topic :: Internet :: WWW/HTTP
Classifier: Programming Language :: Python :: 3
Classifier: Programming Language :: Python :: 3.7
Classifier: Programming Language :: Python :: 3.8
Classifier: Programming Language :: Python :: 3.9
Classifier: Programming Language :: Python :: 3.10
Classifier: Programming Language :: Python :: 3 :: Only
Requires-Python: >=3.7
License-File: LICENSE
Requires-Dist: sqlalchemy <1.5,>=1.4.42
Provides-Extra: aiomysql
Requires-Dist: aiomysql ; extra == 'aiomysql'
Provides-Extra: aiopg
Requires-Dist: aiopg ; extra == 'aiopg'
Provides-Extra: aiosqlite
Requires-Dist: aiosqlite ; extra == 'aiosqlite'
Provides-Extra: asyncmy
Requires-Dist: asyncmy ; extra == 'asyncmy'
Provides-Extra: asyncpg
Requires-Dist: asyncpg ; extra == 'asyncpg'
Provides-Extra: mysql
Requires-Dist: aiomysql ; extra == 'mysql'
Provides-Extra: postgresql
Requires-Dist: asyncpg ; extra == 'postgresql'
Provides-Extra: sqlite
Requires-Dist: aiosqlite ; extra == 'sqlite'
